AUTHORS.rst
CHANGES.rst
HGREV
LICENSE.txt
MANIFEST.in
README.rst
TODO.rst
setup.py
adminfiles/__init__.py
adminfiles/admin.py
adminfiles/flickr.py
adminfiles/listeners.py
adminfiles/models.py
adminfiles/parse.py
adminfiles/settings.py
adminfiles/urls.py
adminfiles/utils.py
adminfiles/views.py
adminfiles/locale/de/LC_MESSAGES/django.mo
adminfiles/locale/de/LC_MESSAGES/django.po
adminfiles/locale/es/LC_MESSAGES/django.mo
adminfiles/locale/es/LC_MESSAGES/django.po
adminfiles/locale/pl/LC_MESSAGES/django.mo
adminfiles/locale/pl/LC_MESSAGES/django.po
adminfiles/locale/ru/LC_MESSAGES/django.mo
adminfiles/locale/ru/LC_MESSAGES/django.po
adminfiles/management/__init__.py
adminfiles/management/commands/__init__.py
adminfiles/management/commands/adminfiles_browser_views.py
adminfiles/management/commands/sync_upload_refs.py
adminfiles/static/adminfiles/adminfiles.css
adminfiles/static/adminfiles/adminfiles.js
adminfiles/static/adminfiles/icon_addlink.gif
adminfiles/static/adminfiles/icon_refreshlink.gif
adminfiles/static/adminfiles/model.js
adminfiles/static/adminfiles/photo-edit.js
adminfiles/static/adminfiles/mimetypes/doc.png
adminfiles/static/adminfiles/mimetypes/empty.png
adminfiles/static/adminfiles/mimetypes/pdf.png
adminfiles/static/adminfiles/mimetypes/xls.png
adminfiles/static/adminfiles/mimetypes/zip.png
adminfiles/templates/adminfiles/render/default.html
adminfiles/templates/adminfiles/render/image/default.html
adminfiles/templates/adminfiles/uploader/base.html
adminfiles/templates/adminfiles/uploader/flickr.html
adminfiles/templates/adminfiles/uploader/video.html
adminfiles/templatetags/__init__.py
adminfiles/templatetags/adminfiles_tags.py
django_adminfiles.egg-info/PKG-INFO
django_adminfiles.egg-info/SOURCES.txt
django_adminfiles.egg-info/dependency_links.txt
django_adminfiles.egg-info/not-zip-safe
django_adminfiles.egg-info/top_level.txt
tests/__init__.py
tests/models.py
tests/runtests.py
tests/test_settings.py
tests/tests.py
tests/urls.py