Metadata-Version: 1.1
Name: django-adminfiles
Version: 1.0.1
Summary: File upload manager and picker for Django admin
Home-page: http://bitbucket.org/carljm/django-adminfiles/
Author: Carl Meyer
Author-email: carl@oddbird.net
License: UNKNOWN
Platform: UNKNOWN
Classifier: Development Status :: 4 - Beta
Classifier: Environment :: Web Environment
Classifier: Intended Audience :: Developers
Classifier: License :: OSI Approved :: BSD License
Classifier: Operating System :: OS Independent
Classifier: Programming Language :: Python
Classifier: Framework :: Django
